myimageprocessingpackage/__init__.py
myimageprocessingpackage/processing/__init__.py
myimageprocessingpackage/processing/combination.py
myimageprocessingpackage/processing/transformation.py
myimageprocessingpackage/utils/__init__.py
myimageprocessingpackage/utils/io.py
myimageprocessingpackage/utils/plot.py
myimageprocessingpackage-0.0.2.dist-info/LICENSE.txt
myimageprocessingpackage-0.0.2.dist-info/METADATA
myimageprocessingpackage-0.0.2.dist-info/WHEEL
myimageprocessingpackage-0.0.2.dist-info/top_level.txt
myimageprocessingpackage-0.0.2.dist-info/RECORD
