Metadata-Version: 2.1
Name: myimageprocessingpackage
Version: 0.0.2
Summary: Image processing package using Skimage
Home-page: https://github.com/vitor-manoel-s/meu-pacote-processamento-de-imagem
Author: Vitor
Requires-Python: >=3.5
License-File: LICENSE.txt
Requires-Dist: matplotlib
Requires-Dist: numpy
Requires-Dist: scikit-image >=0.16.1
